{"commit_hash": "c7e65b4872fea6ef36dd37717517c7501d066dee", "env_name": "virtualenv-py3.10-Cython-build-packaging", "date": 1733147100000, "params": {"machine": "gh-runner", "python": "3.10", "Cython": "", "build": "", "packaging": ""}, "python": "3.10", "requirements": {"Cython": "", "build": "", "packaging": ""}, "env_vars": {}, "result_columns": ["result", "params", "version", "started_at", "duration", "stats_ci_99_a", "stats_ci_99_b", "stats_q_25", "stats_q_75", "stats_number", "stats_repeat", "samples", "profile"], "results": {"benchmarks.time_computation": [[3.737528687000008], [], "089635b7375b19f5c790c7337625b200db3327a27d63c756ac5dbb4c1fc25b62", 1733147228508, 25.766, [0.063753], [5.5557], [1.2152], [4.3594], [1], [7]], "benchmarks.mem_list": [[2008], [], "a31e7e31a99db6599fc29032ea5a3cb9782922117f13e122a69c2745a93c3d32", 1733147228500, 0.007792]}, "durations": {}, "version": 2}